XeroML/__init__.py
XeroML/run.py
XeroML/XeroGraph/__init__.py
XeroML/XeroGraph/compare.py
XeroML/XeroGraph/main.py
XeroML/XeroGraph/utils.py
XeroML/XeroGraph/xputer_main.py
XeroML/data/Isotope_abundance.txt
XeroML/models/__init__.py
XeroML/models/abc.py
XeroML/models/all.py
XeroML/models/cbc.py
XeroML/models/etc.py
XeroML/models/gbc.py
XeroML/models/hgb.py
XeroML/models/lgb.py
XeroML/models/mlp.py
XeroML/models/rfc.py
XeroML/models/sen.py
XeroML/models/sl1.py
XeroML/models/sl2.py
XeroML/models/svc.py
XeroML/models/svn.py
XeroML/models/tab.py
XeroML/models/xgb.py
XeroML/utils/__init__.py
XeroML/utils/all_ml.py
XeroML/utils/deeplink.py
XeroML/utils/metrics.py
XeroML/utils/prep.py
XeroML/utils/run_model.py
XeroML/utils/utils.py
XeroML/utils/binary_tabnet/__init__.py
XeroML/utils/binary_tabnet/abstract_model.py
XeroML/utils/binary_tabnet/callbacks.py
XeroML/utils/binary_tabnet/metrics.py
XeroML/utils/binary_tabnet/multiclass_utils.py
XeroML/utils/binary_tabnet/pretraining.py
XeroML/utils/binary_tabnet/pretraining_utils.py
XeroML/utils/binary_tabnet/sparsemax.py
XeroML/utils/binary_tabnet/tab_model.py
XeroML/utils/binary_tabnet/tab_network.py
XeroML/utils/binary_tabnet/utils.py
XeroML/xApp/__init__.py
XeroML/xApp/utils.py
XeroML-0.0.3.dist-info/LICENSE
XeroML-0.0.3.dist-info/METADATA
XeroML-0.0.3.dist-info/WHEEL
XeroML-0.0.3.dist-info/top_level.txt
XeroML-0.0.3.dist-info/RECORD
